{
  "ok": false,
  "error": "",
  "scheduled_message_id": "Q00000000",
  "channel": "C00000000",
  "post_at": 12345,
  "message": {
    "bot_id": "B00000000",
    "type": "",
    "text": "",
    "user": "U00000000",
    "attachments": [
      {
        "text": "",
        "id": 12345,
        "fallback": ""
      }
    ],
    "blocks": [
      {
        "type": "",
        "block_id": "12345",
        "image_url": "https://www.example.com/",
        "alt_text": "",
        "title": {
          "type": "",
          "text": "",
          "emoji": false
        },
        "fallback": "",
        "image_width": 12345,
        "image_height": 12345,
        "image_bytes": 12345
      }
    ]
  },
  "needed": "",
  "provided": ""
}